easyebay/.DS_Store
easyebay/README.md
easyebay/__init__.py
easyebay/_extract_from _html_legacy.py
easyebay/requirements.txt
easyebay/search.py
easyebay/util.py
easyebay-0.1.1.dist-info/METADATA
easyebay-0.1.1.dist-info/WHEEL
easyebay-0.1.1.dist-info/RECORD
