Metadata-Version: 2.1
Name: easyebay
Version: 0.1.1
Summary: A library for scraping items from eBay
Author: DrEgg
Author-email: public@dregg.me
Requires-Python: >=3.8,<4.0
Classifier: Programming Language :: Python :: 3
Classifier: Programming Language :: Python :: 3.8
Classifier: Programming Language :: Python :: 3.9
Classifier: Programming Language :: Python :: 3.10
Classifier: Programming Language :: Python :: 3.11
Requires-Dist: beautifulsoup4 (>=4.12.2,<5.0.0)
Requires-Dist: requests (>=2.31.0,<3.0.0)
